MANIFEST.in
setup.py
external/TextDetection.cpp
external/TextDetection.h
lsocr/__init__.py
pyLSOCR.egg-info/PKG-INFO
pyLSOCR.egg-info/SOURCES.txt
pyLSOCR.egg-info/dependency_links.txt
pyLSOCR.egg-info/requires.txt
pyLSOCR.egg-info/top_level.txt
src/_pyLSOCR.cpp
src/opencv_helpers.h