Metadata-Version: 1.0
Name: pyLSOCR
Version: 0.1.4
Summary: A python wrapper
Home-page: UNKNOWN
Author: Lingospot
Author-email: info@lingospot.com
License: See separate LICENSE file
Platform: UNKNOWN
Classifier: License :: Other/Proprietary License
Classifier: Development Status :: 3 - Alpha
Classifier: Topic :: Scientific/Engineering
